girder_zip_extractor/__init__.py
girder_zip_extractor-0.4.0.dist-info/LICENSE
girder_zip_extractor-0.4.0.dist-info/METADATA
girder_zip_extractor-0.4.0.dist-info/WHEEL
girder_zip_extractor-0.4.0.dist-info/entry_points.txt
girder_zip_extractor-0.4.0.dist-info/top_level.txt
girder_zip_extractor-0.4.0.dist-info/RECORD
