Metadata-Version: 2.1
Name: girder_zip_extractor
Version: 0.4.0
Summary: A girder plugin to extract the uploaded zip files
Home-page: https://github.com/girder/girder_zip_extractor
Author: Parth Sanghani
Author-email: pas353@pitt.edu
License: Apache Software License 2.0
Keywords: girder-plugin,girder_zip_extractor
Classifier: Development Status :: 2 - Pre-Alpha
Classifier: License :: OSI Approved :: Apache Software License
Classifier: Natural Language :: English
Classifier: Programming Language :: Python :: 3
Classifier: Programming Language :: Python :: 3.6
Classifier: Programming Language :: Python :: 3.7
Classifier: Programming Language :: Python :: 3.8
License-File: LICENSE
Requires-Dist: girder>=3.0.0a1
